aiogram_ydb_storage/__init__.py
aiogram_ydb_storage/storage.py
aiogram_ydb_storage-0.1.0.dist-info/LICENSE
aiogram_ydb_storage-0.1.0.dist-info/METADATA
aiogram_ydb_storage-0.1.0.dist-info/WHEEL
aiogram_ydb_storage-0.1.0.dist-info/RECORD
