Metadata-Version: 2.1
Name: aiogram-ydb-storage
Version: 0.1.0
Summary: FSM Storage for YDB (Yandex Database)
License: MIT
Author: Dmitry (DevDK)
Author-email: Dmitry@kolyadin.me
Requires-Python: >=3.12,<4.0
Classifier: License :: OSI Approved :: MIT License
Classifier: Programming Language :: Python :: 3
Requires-Dist: aiogram (>=3.0.0,<4.0.0)
Requires-Dist: ydb[yc] (==3.5.0)
